mxshare/__init__.py
mxshare/fci/__init__.py
mxshare/fci/contract_info_cffex.py
mxshare/fci/contract_info_czce.py
mxshare/fci/contract_info_dce.py
mxshare/fci/contract_info_gfex.py
mxshare/fci/contract_info_ine.py
mxshare/fci/contract_info_shfe.py
mxshare/fci/contract_info_szse.py
mxshare/fci/load_contract_info.py
mxshare-0.0.6.dist-info/LICENSE
mxshare-0.0.6.dist-info/METADATA
mxshare-0.0.6.dist-info/WHEEL
mxshare-0.0.6.dist-info/top_level.txt
mxshare-0.0.6.dist-info/RECORD
