Metadata-Version: 2.1
Name: mxshare
Version: 0.0.6
Summary: python share
Author-email: mxxu <17611379220@163.com>
License: MIT
Requires-Python: >=3.6
License-File: LICENSE
Requires-Dist: requests>=2.25.0
